LICENSE.BAYKIT
README.md
setup.py
bayserver_docker_http3/__init__.py
bayserver_docker_http3/h3_docker.py
bayserver_docker_http3/h3_protocol_handler.py
bayserver_docker_http3/h3port_docker.py
bayserver_docker_http3/qic_ticket.py
bayserver_docker_http3/quic_connection_protocol_ex.py
bayserver_docker_http3.egg-info/PKG-INFO
bayserver_docker_http3.egg-info/SOURCES.txt
bayserver_docker_http3.egg-info/dependency_links.txt
bayserver_docker_http3.egg-info/requires.txt
bayserver_docker_http3.egg-info/top_level.txt