Metadata-Version: 1.2
Name: bayserver-docker-http3
Version: 3.0.0
Summary: HTTP3 docker for BayServer
Home-page: https://baykit.yokohama/
Author: Michisuke-P
Author-email: michisukep@gmail.com
License: MIT
Platform: UNKNOWN
Requires-Python: >=3.7
